odoo/addons/account_move_transfer_partner/README.rst
odoo/addons/account_move_transfer_partner/__init__.py
odoo/addons/account_move_transfer_partner/__manifest__.py
odoo/addons/account_move_transfer_partner/i18n/account_move_transfer_partner.pot
odoo/addons/account_move_transfer_partner/readme/CONTRIBUTORS.rst
odoo/addons/account_move_transfer_partner/readme/DESCRIPTION.rst
odoo/addons/account_move_transfer_partner/readme/USAGE.rst
odoo/addons/account_move_transfer_partner/security/ir.model.access.csv
odoo/addons/account_move_transfer_partner/static/description/icon.png
odoo/addons/account_move_transfer_partner/static/description/index.html
odoo/addons/account_move_transfer_partner/tests/__init__.py
odoo/addons/account_move_transfer_partner/tests/test_account_move_transfer_partner.py
odoo/addons/account_move_transfer_partner/wizard/__init__.py
odoo/addons/account_move_transfer_partner/wizard/wizard_account_move_transfer_partner.py
odoo/addons/account_move_transfer_partner/wizard/wizard_account_move_transfer_partner_view.xml
odoo14_addon_account_move_transfer_partner-14.0.1.0.1.dist-info/METADATA
odoo14_addon_account_move_transfer_partner-14.0.1.0.1.dist-info/WHEEL
odoo14_addon_account_move_transfer_partner-14.0.1.0.1.dist-info/top_level.txt
odoo14_addon_account_move_transfer_partner-14.0.1.0.1.dist-info/RECORD
