Metadata-Version: 2.1
Name: odoo14-addon-account-move-transfer-partner
Version: 14.0.1.0.1
Summary: Automation to translate amount due from many partners to one partner
Home-page: https://github.com/OCA/account-financial-tools
Author: ForgeFlow S.L., Odoo Community Association (OCA)
Author-email: support@odoo-community.org
License: AGPL-3
Platform: UNKNOWN
Classifier: Programming Language :: Python
Classifier: Framework :: Odoo
Classifier: Framework :: Odoo :: 14.0
Classifier: License :: OSI Approved :: GNU Affero General Public License v3
Classifier: Development Status :: 3 - Alpha
Requires-Python: >=3.6
Requires-Dist: odoo <14.1dev,>=14.0a
